{
  "cli_version": "0.6.3",
  "checkpoint_id": "c2e43c9f1eda",
  "session_id": "019ed3cc-ee55-7b44-9f6c-ab7e8bc48efb",
  "strategy": "manual-commit",
  "created_at": "2026-06-17T04:23:33.589365457Z",
  "branch": "master",
  "checkpoints_count": 1,
  "files_touched": [
    "src/components/TopBar.astro",
    "src/data/experiments.ts",
    "src/layouts/CanvasLayout.astro",
    "src/layouts/PageLayout.astro",
    "src/pages/complex.astro",
    "src/pages/index.astro",
    "src/pages/symmetry.astro",
    "src/pages/voronoi.astro",
    "src/styles/global.css"
  ],
  "agent": "Pi",
  "model": "",
  "turn_id": "d5cac7795abd",
  "token_usage": {
    "input_tokens": 51330,
    "cache_creation_tokens": 0,
    "cache_read_tokens": 478720,
    "output_tokens": 7619,
    "api_call_count": 26
  },
  "session_metrics": {
    "turn_count": 1
  },
  "initial_attribution": {
    "calculated_at": "2026-06-17T04:23:33.584650647Z",
    "agent_lines": 258,
    "agent_removed": 197,
    "human_added": 0,
    "human_modified": 0,
    "human_removed": 0,
    "total_committed": 258,
    "total_lines_changed": 455,
    "agent_percentage": 100,
    "metric_version": 2
  },
  "prompt_attributions": [
    {
      "checkpoint_number": 1,
      "user_lines_added": 0,
      "user_lines_removed": 0,
      "agent_lines_added": 0,
      "agent_lines_removed": 0
    }
  ]
}
